DBQuery-0.4.1.dist-info/DESCRIPTION.rst
DBQuery-0.4.1.dist-info/METADATA
DBQuery-0.4.1.dist-info/RECORD
DBQuery-0.4.1.dist-info/WHEEL
DBQuery-0.4.1.dist-info/metadata.json
DBQuery-0.4.1.dist-info/top_level.txt
dbquery/__init__.py
dbquery/db.py
dbquery/log_msg.py
dbquery/postgres.py
dbquery/query.py
dbquery/sqlite.py
