Metadata-Version: 2.0
Name: DBQuery
Version: 0.4.1
Summary: Simplify your database access.
Home-page: https://github.com/merry-bits/DBQuery
Author: merry-bits
Author-email: merry-bits@users.noreply.github.com
License: GPLv2
Keywords: easy database access SQLite PostgreSQL wrap SQL connection query
Platform: UNKNOWN
Classifier: Development Status :: 5 - Production/Stable
Classifier: Intended Audience :: Developers
Classifier: Topic :: Database :: Front-Ends
Classifier: Natural Language :: English
Classifier: License :: OSI Approved :: GNU General Public License v2 (GPLv2)
Classifier: Programming Language :: Python
Classifier: Programming Language :: Python :: 2.7
Classifier: Programming Language :: Python :: 3.3
Classifier: Programming Language :: Python :: 3.4
Classifier: Programming Language :: Python :: 3.5
Provides-Extra: postgres
Requires-Dist: psycopg2 (>=2.6.2); extra == 'postgres'
